susantomo/__init__.py
susantomo/bibtex.py
susantomo/constants.py
susantomo/convert.py
susantomo/objects.py
susantomo/protocols.conf
susantomo/viewers.py
susantomo/wizards.py
susantomo/protocols/__init__.py
susantomo/protocols/protocol_average.py
susantomo/protocols/protocol_base.py
susantomo/protocols/protocol_estimate_ctf.py
susantomo/protocols/protocol_mra.py
susantomo/protocols/protocol_subset.py
susantomo/scripts/__init__.py
susantomo/scripts/average.py
susantomo/scripts/base.py
susantomo/scripts/estimate_ctf.py
susantomo/scripts/mra.py
susantomo/scripts/subsets.py
susantomo/tests/__init__.py
susantomo/tests/test_protocols.py
scipion_em_susantomo-3.0b5.dist-info/LICENSE
scipion_em_susantomo-3.0b5.dist-info/METADATA
scipion_em_susantomo-3.0b5.dist-info/WHEEL
scipion_em_susantomo-3.0b5.dist-info/entry_points.txt
scipion_em_susantomo-3.0b5.dist-info/top_level.txt
scipion_em_susantomo-3.0b5.dist-info/RECORD
